{"batchNumber":426,"issues":[{"number":1875,"title":"DefaultChatOptions should not be an inner class ChatOptionsBuilder, the build method should be inside the interface ChatOptions","body":"This is similar to how we have ChatClient.\r\n\r\n\r\nWe can deprecate the top level ChatOptionsBuilder class and have the two sit side by side for one release cycle.\r\n","state":"CLOSED","createdAt":[2024,12,5,16,51,2],"updatedAt":[2024,12,12,15,12,51],"closedAt":[2024,12,12,15,12,50],"url":"https://github.com/spring-projects/spring-ai/issues/1875","author":{"login":"markpollack","name":"Mark Pollack"},"comments":[],"labels":[{"name":"design","color":"bfdadc","description":""}]}],"timestamp":"2025-07-24_17-14-48"}