{"batchNumber":428,"issues":[{"number":1865,"title":"Cohere embeddings in milestone 4 release","body":"**Bug description**\r\nUsing the model name as `cohere.embed-english-v3` fails when using milestone 4 with an upstream error in Bedrock: “:03:38.223+01:00 ERROR 33643 --- [nio-8080-exec-3] o.a.c.c.C.[.[.[/].[dispatcherServlet]    : Servlet.service() for servlet [dispatcherServlet] in context with path [] threw exception [Request processing failed: nl.sig.chat_api.exception_handling.QueryEmbeddingException: Failed to embed the query Write a long text about a cat. Reason: The provided model identifier is invalid. (Service: BedrockRuntime, Status Code: 400, Request ID: )] with root cause.”\r\n\r\n**Environment**\r\nJava 23, Spring AI 1.0.0-M4\r\n\r\n**Steps to reproduce**\r\nTrying to embed a text fails when using milestone 4 works perfectly fine in M3.\r\n\r\n**Expected behavior**\r\nEmbedding should work while using the correct model name.\r\n","state":"CLOSED","createdAt":[2024,12,4,18,22,30],"updatedAt":[2024,12,4,23,6,8],"closedAt":[2024,12,4,23,6,7],"url":"https://github.com/spring-projects/spring-ai/issues/1865","author":{"login":"bruno-oliveira","name":"Bruno Oliveira"},"comments":[{"author":{"login":"bruno-oliveira","name":"Bruno Oliveira"},"body":"My bad! All works!","createdAt":[2024,12,4,23,6,7]}],"labels":[]}],"timestamp":"2025-07-24_17-14-48"}